<?xml version="1.0" encoding="utf-8"?><toc><breadcrumbs><li><a href="b75aa289-6b32-4eff-a256-8c84ae13447e.htm">Docs</a></li><li><a href="cf27bbf5-cd48-c48a-04b7-212712fe2996.htm">Mbcs<wbr />Central</a></li><li><a href="dfb185f3-994f-8ab9-9ba0-b5cb6b97eb80.htm">Native<wbr />Methods</a></li></breadcrumbs><tocItems><li><a id="5e4daa3c-7408-de4b-f514-adafe07ecb55" class="has-submenu" href="5e4daa3c-7408-de4b-f514-adafe07ecb55.htm"><span data-tocFile="../toc/IDA01D0F.xml" class="icon toggle" onclick="ToggleExpandCollapse(this); return false;"><i class="fa fa-angle-right"> </i></span>Methods</a><ul class="toc-menu is-hidden"> </ul></li></tocItems></toc>