<?xml version="1.0" encoding="utf-8"?><toc><breadcrumbs><li><a href="b75aa289-6b32-4eff-a256-8c84ae13447e.htm">Docs</a></li><li><a href="cf27bbf5-cd48-c48a-04b7-212712fe2996.htm">Mbcs<wbr />Central</a></li><li><a href="aaa4d033-afa2-22fe-f475-a13c6ef88632.htm">Document<wbr />Layout<wbr />Fields</a></li></breadcrumbs><tocItems><li><a id="a6b5a315-de4f-61f6-df3d-f3a57814bd45" href="a6b5a315-de4f-61f6-df3d-f3a57814bd45.htm">Document<wbr />Layout<wbr />Fields</a></li><li><a id="1112a103-6070-6ed2-e265-74eae0d2fced" class="has-submenu" href="1112a103-6070-6ed2-e265-74eae0d2fced.htm"><span data-tocFile="../toc/IDB0EB0F.xml" class="icon toggle" onclick="ToggleExpandCollapse(this); return false;"><i class="fa fa-angle-right"> </i></span>Constructors</a><ul class="toc-menu is-hidden"> </ul></li><li><a id="90976fc8-e8f6-0172-0c39-3cbd48e4f594" class="has-submenu" href="90976fc8-e8f6-0172-0c39-3cbd48e4f594.htm"><span data-tocFile="../toc/IDC0EB0F.xml" class="icon toggle" onclick="ToggleExpandCollapse(this); return false;"><i class="fa fa-angle-right"> </i></span>Properties</a><ul class="toc-menu is-hidden"> </ul></li><li><a id="de29bfa9-b7fe-d473-55f0-9d2aefe2239b" class="has-submenu" href="de29bfa9-b7fe-d473-55f0-9d2aefe2239b.htm"><span data-tocFile="../toc/IDD0EB0F.xml" class="icon toggle" onclick="ToggleExpandCollapse(this); return false;"><i class="fa fa-angle-right"> </i></span>Methods</a><ul class="toc-menu is-hidden"> </ul></li><li><a id="79598bba-cd4b-51c1-f029-352889e97156" class="has-submenu" href="79598bba-cd4b-51c1-f029-352889e97156.htm"><span data-tocFile="../toc/IDE0EB0F.xml" class="icon toggle" onclick="ToggleExpandCollapse(this); return false;"><i class="fa fa-angle-right"> </i></span>Events</a><ul class="toc-menu is-hidden"> </ul></li><li><a id="3fdbeb38-4620-758c-04d0-4bbdd69bf229" class="has-submenu" href="3fdbeb38-4620-758c-04d0-4bbdd69bf229.htm"><span data-tocFile="../toc/IDF0EB0F.xml" class="icon toggle" onclick="ToggleExpandCollapse(this); return false;"><i class="fa fa-angle-right"> </i></span>Fields</a><ul class="toc-menu is-hidden"> </ul></li></tocItems></toc>