<?xml version="1.0" encoding="utf-8"?><toc><breadcrumbs><li><a href="b75aa289-6b32-4eff-a256-8c84ae13447e.htm">Docs</a></li><li><a href="cf27bbf5-cd48-c48a-04b7-212712fe2996.htm">Mbcs<wbr />Central</a></li><li><a href="7214fc49-047a-e52e-96ba-ce9de808ee8e.htm">frm<wbr />Report<wbr />Dispatcher</a></li></breadcrumbs><tocItems><li><a id="af46ed25-67a7-6927-bf6f-c814704e7f02" class="has-submenu" href="af46ed25-67a7-6927-bf6f-c814704e7f02.htm"><span data-tocFile="../toc/IDA0LC0F.xml" class="icon toggle" onclick="ToggleExpandCollapse(this); return false;"><i class="fa fa-angle-right"> </i></span>Constructors</a><ul class="toc-menu is-hidden"> </ul></li><li><a id="95c1baf4-0e5a-64ca-a064-7e9207a8a0e7" class="has-submenu" href="95c1baf4-0e5a-64ca-a064-7e9207a8a0e7.htm"><span data-tocFile="../toc/IDB0LC0F.xml" class="icon toggle" onclick="ToggleExpandCollapse(this); return false;"><i class="fa fa-angle-right"> </i></span>Properties</a><ul class="toc-menu is-hidden"> </ul></li><li><a id="c8320fbd-375a-48fa-3900-532bb0c70b42" class="has-submenu" href="c8320fbd-375a-48fa-3900-532bb0c70b42.htm"><span data-tocFile="../toc/IDC0LC0F.xml" class="icon toggle" onclick="ToggleExpandCollapse(this); return false;"><i class="fa fa-angle-right"> </i></span>Methods</a><ul class="toc-menu is-hidden"> </ul></li><li><a id="9d623d89-ef4a-1e62-5113-15ff599bb935" href="9d623d89-ef4a-1e62-5113-15ff599bb935.htm">Events</a></li><li><a id="017e9741-68f5-346b-633c-b5ac4211e9cb" class="has-submenu" href="017e9741-68f5-346b-633c-b5ac4211e9cb.htm"><span data-tocFile="../toc/IDE0LC0F.xml" class="icon toggle" onclick="ToggleExpandCollapse(this); return false;"><i class="fa fa-angle-right"> </i></span>Fields</a><ul class="toc-menu is-hidden"> </ul></li></tocItems></toc>