<?xml version="1.0" encoding="utf-8"?><toc><breadcrumbs><li><a href="b75aa289-6b32-4eff-a256-8c84ae13447e.htm">Docs</a></li><li><a href="f0b6540e-51a1-647f-e9c6-e1eb4309314f.htm">Mbcs<wbr />Central.<wbr />Win<wbr />GL</a></li><li><a href="8d78387e-e1f4-4190-df89-9da30dcc125a.htm">Trial<wbr />Balance<wbr />Parms</a></li></breadcrumbs><tocItems><li><a id="ec6fb46d-a2d7-e38b-cdcd-4fd811fc5509" href="ec6fb46d-a2d7-e38b-cdcd-4fd811fc5509.htm">Constructor</a></li><li><a id="b6b7ea4c-86ab-d64c-de24-9ca0e50695dc" class="has-submenu" href="b6b7ea4c-86ab-d64c-de24-9ca0e50695dc.htm"><span data-tocFile="../toc/IDB0LE0O.xml" class="icon toggle" onclick="ToggleExpandCollapse(this); return false;"><i class="fa fa-angle-right"> </i></span>Properties</a><ul class="toc-menu is-hidden"> </ul></li><li><a id="6d3c5634-6846-179e-96c9-f48eb1d20ac2" class="has-submenu" href="6d3c5634-6846-179e-96c9-f48eb1d20ac2.htm"><span data-tocFile="../toc/IDC0LE0O.xml" class="icon toggle" onclick="ToggleExpandCollapse(this); return false;"><i class="fa fa-angle-right"> </i></span>Methods</a><ul class="toc-menu is-hidden"> </ul></li></tocItems></toc>