<?xml version="1.0" encoding="utf-8"?><toc><breadcrumbs><li><a href="b75aa289-6b32-4eff-a256-8c84ae13447e.htm">Docs</a></li><li><a href="f0b6540e-51a1-647f-e9c6-e1eb4309314f.htm">Mbcs<wbr />Central.<wbr />Win<wbr />GL</a></li><li><a href="cfbbdbb4-5a4f-7a76-e933-051a228c162e.htm">Accounts</a></li></breadcrumbs><tocItems><li><a id="4f661e85-14a2-8f7e-aba7-3f3c4c19944b" href="4f661e85-14a2-8f7e-aba7-3f3c4c19944b.htm">Accounts</a></li><li><a id="5848d037-0670-05b4-a53d-e6ab54354b85" class="has-submenu" href="5848d037-0670-05b4-a53d-e6ab54354b85.htm"><span data-tocFile="../toc/IDBCO.xml" class="icon toggle" onclick="ToggleExpandCollapse(this); return false;"><i class="fa fa-angle-right"> </i></span>Constructors</a><ul class="toc-menu is-hidden"> </ul></li><li><a id="e9de5117-fa5b-51a5-bb2b-0789dba1a9f7" class="has-submenu" href="e9de5117-fa5b-51a5-bb2b-0789dba1a9f7.htm"><span data-tocFile="../toc/IDCCO.xml" class="icon toggle" onclick="ToggleExpandCollapse(this); return false;"><i class="fa fa-angle-right"> </i></span>Properties</a><ul class="toc-menu is-hidden"> </ul></li><li><a id="17e15489-ed8d-667c-9a9f-c527c706ebdd" class="has-submenu" href="17e15489-ed8d-667c-9a9f-c527c706ebdd.htm"><span data-tocFile="../toc/IDDCO.xml" class="icon toggle" onclick="ToggleExpandCollapse(this); return false;"><i class="fa fa-angle-right"> </i></span>Methods</a><ul class="toc-menu is-hidden"> </ul></li><li><a id="f5379573-c521-8fb3-fef6-d9f6d9cfbb73" class="has-submenu" href="f5379573-c521-8fb3-fef6-d9f6d9cfbb73.htm"><span data-tocFile="../toc/IDECO.xml" class="icon toggle" onclick="ToggleExpandCollapse(this); return false;"><i class="fa fa-angle-right"> </i></span>Events</a><ul class="toc-menu is-hidden"> </ul></li><li><a id="daf0af60-d3ca-158f-b5a3-4c255b700c54" class="has-submenu" href="daf0af60-d3ca-158f-b5a3-4c255b700c54.htm"><span data-tocFile="../toc/IDFCO.xml" class="icon toggle" onclick="ToggleExpandCollapse(this); return false;"><i class="fa fa-angle-right"> </i></span>Fields</a><ul class="toc-menu is-hidden"> </ul></li></tocItems></toc>