<?xml version="1.0" encoding="utf-8"?><toc><breadcrumbs><li><a href="b75aa289-6b32-4eff-a256-8c84ae13447e.htm">Docs</a></li><li><a href="f0b6540e-51a1-647f-e9c6-e1eb4309314f.htm">Mbcs<wbr />Central.<wbr />Win<wbr />GL</a></li><li><a href="30563376-64da-2d81-4997-5246a736ce67.htm">Ap<wbr />Trans</a></li></breadcrumbs><tocItems><li><a id="eb22c52f-0916-cd27-e3d1-b82ae236fc1d" href="eb22c52f-0916-cd27-e3d1-b82ae236fc1d.htm">Ap<wbr />Trans</a></li><li><a id="c1767ae5-be84-0ff3-7c65-4c7af78c3e11" class="has-submenu" href="c1767ae5-be84-0ff3-7c65-4c7af78c3e11.htm"><span data-tocFile="../toc/IDBEO.xml" class="icon toggle" onclick="ToggleExpandCollapse(this); return false;"><i class="fa fa-angle-right"> </i></span>Constructors</a><ul class="toc-menu is-hidden"> </ul></li><li><a id="f0bfa3f7-5588-6f4c-0644-5127f69df343" class="has-submenu" href="f0bfa3f7-5588-6f4c-0644-5127f69df343.htm"><span data-tocFile="../toc/IDCEO.xml" class="icon toggle" onclick="ToggleExpandCollapse(this); return false;"><i class="fa fa-angle-right"> </i></span>Properties</a><ul class="toc-menu is-hidden"> </ul></li><li><a id="0d8d8d99-630a-fc41-aa4c-598bfe2bfae4" class="has-submenu" href="0d8d8d99-630a-fc41-aa4c-598bfe2bfae4.htm"><span data-tocFile="../toc/IDDEO.xml" class="icon toggle" onclick="ToggleExpandCollapse(this); return false;"><i class="fa fa-angle-right"> </i></span>Methods</a><ul class="toc-menu is-hidden"> </ul></li><li><a id="33b5d40c-d4ec-07ce-09ce-c4e9dc5b2521" class="has-submenu" href="33b5d40c-d4ec-07ce-09ce-c4e9dc5b2521.htm"><span data-tocFile="../toc/IDEEO.xml" class="icon toggle" onclick="ToggleExpandCollapse(this); return false;"><i class="fa fa-angle-right"> </i></span>Events</a><ul class="toc-menu is-hidden"> </ul></li><li><a id="c1984725-79ac-c56e-f1e2-d63a4e7ecc33" class="has-submenu" href="c1984725-79ac-c56e-f1e2-d63a4e7ecc33.htm"><span data-tocFile="../toc/IDFEO.xml" class="icon toggle" onclick="ToggleExpandCollapse(this); return false;"><i class="fa fa-angle-right"> </i></span>Fields</a><ul class="toc-menu is-hidden"> </ul></li></tocItems></toc>