<?xml version="1.0" encoding="utf-8"?><toc><breadcrumbs><li><a href="b75aa289-6b32-4eff-a256-8c84ae13447e.htm">Docs</a></li><li><a href="cf27bbf5-cd48-c48a-04b7-212712fe2996.htm">Mbcs<wbr />Central</a></li><li><a href="380eb0d7-0695-adf7-6cd7-8d7784e1a219.htm">Classes</a></li></breadcrumbs><tocItems><li><a id="cdcc0b8b-8ad6-79cd-7ac1-2902aeed778c" href="cdcc0b8b-8ad6-79cd-7ac1-2902aeed778c.htm">Classes</a></li><li><a id="4f28d33c-acf9-f1a4-43b3-a7d83599d197" class="has-submenu" href="4f28d33c-acf9-f1a4-43b3-a7d83599d197.htm"><span data-tocFile="../toc/IDBOF.xml" class="icon toggle" onclick="ToggleExpandCollapse(this); return false;"><i class="fa fa-angle-right"> </i></span>Constructors</a><ul class="toc-menu is-hidden"> </ul></li><li><a id="5709a540-6bcd-da03-0b56-ae0c11a7df07" class="has-submenu" href="5709a540-6bcd-da03-0b56-ae0c11a7df07.htm"><span data-tocFile="../toc/IDCOF.xml" class="icon toggle" onclick="ToggleExpandCollapse(this); return false;"><i class="fa fa-angle-right"> </i></span>Properties</a><ul class="toc-menu is-hidden"> </ul></li><li><a id="95e30ef6-19a0-3120-68b4-c22b54ad76c1" class="has-submenu" href="95e30ef6-19a0-3120-68b4-c22b54ad76c1.htm"><span data-tocFile="../toc/IDDOF.xml" class="icon toggle" onclick="ToggleExpandCollapse(this); return false;"><i class="fa fa-angle-right"> </i></span>Methods</a><ul class="toc-menu is-hidden"> </ul></li><li><a id="98585f2a-f7e3-1a25-2c7b-1a9f03a8bec4" class="has-submenu" href="98585f2a-f7e3-1a25-2c7b-1a9f03a8bec4.htm"><span data-tocFile="../toc/IDEOF.xml" class="icon toggle" onclick="ToggleExpandCollapse(this); return false;"><i class="fa fa-angle-right"> </i></span>Events</a><ul class="toc-menu is-hidden"> </ul></li><li><a id="ecc9dbd2-c197-2b02-ff6f-dadc6de9f542" class="has-submenu" href="ecc9dbd2-c197-2b02-ff6f-dadc6de9f542.htm"><span data-tocFile="../toc/IDFOF.xml" class="icon toggle" onclick="ToggleExpandCollapse(this); return false;"><i class="fa fa-angle-right"> </i></span>Fields</a><ul class="toc-menu is-hidden"> </ul></li></tocItems></toc>